{
  "id": "carlsen_seed_mnbu17u4_e69xh4",
  "createdAt": "2026-03-29T14:06:17.068Z",
  "result": "unknown",
  "fen": "5r2/6k1/8/p3N1P1/P5b1/4P3/4P3/5K2 w - - 0 31",
  "pgn": "[Event \"?\"]\n[Site \"?\"]\n[Date \"????.??.??\"]\n[Round \"?\"]\n[White \"?\"]\n[Black \"?\"]\n[Result \"*\"]\n\n1. c4 c5 2. Nc3 Nc6 3. g3 g6 4. Bg2 Bg7 5. Nf3 Nf6 6. Nd5 O-O 7. Nxf6+ Kh8 8. Nxh7 Bxb2 9. O-O Bxc1 10. d4 cxd4 11. Rxc1 d5 12. Qxd4+ f6 13. cxd5 e5 14. dxc6 e4 15. Qxf6+ Kxh7 16. Qg7+ Kxg7 17. Ne5 e3 18. cxb7 Bxb7 19. fxe3 Qd5 20. Bxd5 Rxf1+ 21. Kxf1 g5 22. Be4 Bd5 23. Rc7+ Kh8 24. Rc8+ Kg7 25. Rg8+ Rxg8 26. a4 a5 27. h4 Rf8+ 28. Bf5 Be4 29. hxg5 Bxf5 30. g4 Bxg4+ *",
  "moves": [
    "c4",
    "c5",
    "Nc3",
    "Nc6",
    "g3",
    "g6",
    "Bg2",
    "Bg7",
    "Nf3",
    "Nf6",
    "Nd5",
    "O-O",
    "Nxf6+",
    "Kh8",
    "Nxh7",
    "Bxb2",
    "O-O",
    "Bxc1",
    "d4",
    "cxd4",
    "Rxc1",
    "d5",
    "Qxd4+",
    "f6",
    "cxd5",
    "e5",
    "dxc6",
    "e4",
    "Qxf6+",
    "Kxh7",
    "Qg7+",
    "Kxg7",
    "Ne5",
    "e3",
    "cxb7",
    "Bxb7",
    "fxe3",
    "Qd5",
    "Bxd5",
    "Rxf1+",
    "Kxf1",
    "g5",
    "Be4",
    "Bd5",
    "Rc7+",
    "Kh8",
    "Rc8+",
    "Kg7",
    "Rg8+",
    "Rxg8",
    "a4",
    "a5",
    "h4",
    "Rf8+",
    "Bf5",
    "Be4",
    "hxg5",
    "Bxf5",
    "g4",
    "Bxg4+"
  ],
  "meta": {
    "source": "master_continuous_seed",
    "masterId": "carlsen",
    "displayName": "Magnus Carlsen",
    "methodology": [
      "Pragmatismo: escolher posições jogáveis e pouco claras",
      "Finais e técnica: converter vantagens mínimas com paciência",
      "Versatilidade de aberturas e evitar preparação estreita do adversário",
      "Resistência e precisão sob pressão de tempo e cansaco"
    ],
    "metrics": {
      "mate": 200000,
      "check": 5200,
      "captureBase": 1750,
      "captureMatMul": 1.05,
      "promotion": 3200,
      "centerSquare": 265,
      "developPiece": 310,
      "castle": 820,
      "centralPawn": 195,
      "rankAdvancePawn": 55,
      "endgameKingCentral": 120
    },
    "maxPlies": 60,
    "continuousLearning": true
  }
}